electra_pytorch/__init__.py
electra_pytorch/electra_pytorch.py
electra_pytorch-0.1.2.dist-info/LICENSE
electra_pytorch-0.1.2.dist-info/METADATA
electra_pytorch-0.1.2.dist-info/WHEEL
electra_pytorch-0.1.2.dist-info/top_level.txt
electra_pytorch-0.1.2.dist-info/RECORD
