Metadata-Version: 2.1
Name: electra-pytorch
Version: 0.1.2
Summary: Electra - Pytorch
Home-page: https://github.com/lucidrains/electra-pytorch
Author: Erik Nijkamp, Phil Wang
Author-email: erik.nijkamp@gmail.com, lucidrains@gmail.com
License: MIT
Keywords: transformers,artificial intelligence,pretraining
Platform: UNKNOWN
Classifier: Development Status :: 4 - Beta
Classifier: Intended Audience :: Developers
Classifier: Topic :: Scientific/Engineering :: Artificial Intelligence
Classifier: License :: OSI Approved :: MIT License
Classifier: Programming Language :: Python :: 3.7
License-File: LICENSE
Requires-Dist: torch (>=1.6.0)
Requires-Dist: transformers (==3.0.2)
Requires-Dist: scipy
Requires-Dist: sklearn
